<annotation>
	<folder>train</folder>
	<filename>pothole55.jpg</filename>
	<path>/home/amenor/seniorProject/potholedatasetCompressed-12.6.20/train/pothole55.jpg</path>
	<source>
		<database>Unknown</database>
	</source>
	<size>
		<width>800</width>
		<height>600</height>
		<depth>1</depth>
	</size>
	<segmented>0</segmented>
	<object>
		<name>pothole</name>
		<pose>Unspecified</pose>
		<truncated>0</truncated>
		<difficult>0</difficult>
		<bndbox>
			<xmin>276</xmin>
			<ymin>397</ymin>
			<xmax>456</xmax>
			<ymax>470</ymax>
		</bndbox>
	</object>
	<object>
		<name>pothole</name>
		<pose>Unspecified</pose>
		<truncated>0</truncated>
		<difficult>0</difficult>
		<bndbox>
			<xmin>325</xmin>
			<ymin>326</ymin>
			<xmax>489</xmax>
			<ymax>390</ymax>
		</bndbox>
	</object>
</annotation>
